hds/__init__.py
hds/plot.py
hds/stat.py
hds-0.1.15.dist-info/licenses/LICENSE
hds-0.1.15.dist-info/METADATA
hds-0.1.15.dist-info/WHEEL
hds-0.1.15.dist-info/top_level.txt
hds-0.1.15.dist-info/RECORD
