Metadata-Version: 2.4
Name: hds
Version: 0.1.15
Summary: Functions for EDA, Statistics and Machine Learning
Home-page: https://github.com/HelloDataScience/hds
Author: HelloDataScience
Author-email: hellodatasciencekorea@gmail.com
License: MIT
Project-URL: Bug Tracker, https://github.com/HelloDataScience/hds/issues
Classifier: Programming Language :: Python :: 3
Classifier: License :: OSI Approved :: MIT License
Classifier: Operating System :: OS Independent
Requires-Python: >=3.11
License-File: LICENSE
Requires-Dist: numpy
Requires-Dist: pandas
Requires-Dist: scipy
Requires-Dist: seaborn
Requires-Dist: matplotlib
Requires-Dist: statsmodels
Requires-Dist: scikit-learn
Requires-Dist: graphviz
Requires-Dist: requests
Requires-Dist: bs4
Requires-Dist: varname
Dynamic: author
Dynamic: author-email
Dynamic: classifier
Dynamic: description
Dynamic: description-content-type
Dynamic: home-page
Dynamic: license
Dynamic: license-file
Dynamic: project-url
Dynamic: requires-dist
Dynamic: requires-python
Dynamic: summary
